pems_api/__init__.py
pems_api/pems_api.py
pems_api-0.1.2.dist-info/METADATA
pems_api-0.1.2.dist-info/WHEEL
pems_api-0.1.2.dist-info/top_level.txt
pems_api-0.1.2.dist-info/RECORD
