Metadata-Version: 2.1
Name: pems-api
Version: 0.1.2
Summary: API for PeMS dataset
Home-page: https://gitlab.medianets.hu/anagy/pems_api
Author: Attila Nagy
Author-email: anagy@hit.bme.hu
License: MIT
Platform: UNKNOWN
Requires-Dist: pandas
Requires-Dist: numpy
Requires-Dist: tqdm
